{
  "configurations": [
    {
      "browse": {
        "databaseFilename": "${workspaceFolder}/.vscode/browse.vc.db",
        "limitSymbolsToIncludedHeaders": false
      },
      "includePath": [
        "/opt/ros/humble/include/**",
        "/home/mohamed/stonefish_ws/src/bluerov_mav2ros/include/**",
        "/home/mohamed/stonefish_ws/src/stonefish_ros2/include/**",
        "/usr/include/**"
      ],
      "name": "ros2",
      "intelliSenseMode": "gcc-x64",
      "compilerPath": "/usr/bin/gcc",
      "cStandard": "gnu11",
      "cppStandard": "c++17"
    }
  ],
  "version": 4
}